{
  "post_id": "13177",
  "site": "inven_lineage_classic",
  "url": "https://www.inven.co.kr/board/lineageclassic/6482/13177",
  "crawled_at": "2026-04-28T16:00:22.415987+00:00",
  "text": "# **아이템, 몬스터, 마법 DB에 화룡의 둥지 정보가 추가되었습니다**\n안녕하세요. 리니지 클래식 인벤입니다.4월 23일(목)에 아이템, 몬스터, 마법 DB가 업데이트되었습니다.이번 업데이트로 화룡의 둥지 신규 몬스터와 관련 아이템, 미티어 스트라이크 등 신규 마법 정보 등이 추가되었습니다.[**[바로가기] 리니지 클래식 인벤 아이템 DB**](https://lineageclassic.inven.co.kr/db/item/)[**[바로가기] 리니지 클래식 인벤 몬스터 DB**](https://lineageclassic.inven.co.kr/db/monster/)[**[바로가기] 리니지 클래식 인벤 마법 DB**](https://lineageclassic.inven.co.kr/db/spell/)DB 이용 오류나 피드백, 건의 사항 등이 있으시면 언제든지 **Rokah** 에게 인벤 쪽지를 보내주시기 바랍니다.감사합니다.\nEXP 376,090 (44%) / 396,001\n인벤러\nRokah\n인벤쪽지 이니힐링 더보기\n펼치기\n메뉴 접기\n  * 아이온2 프로필\n\n\n**메일 :**Rokah@inven.co.kr**쪽지 :** 관련 문의 및 제보는 쪽지를 보내주세요.\n\n\n\n레벨\n\n\n라이센스\n\n\n경험치\n     376,090 (44%) / 396,001  ( 다음 레벨까지 19,911 / 마격까지 18,110 남음 )  \n\n포인트\n    \n이니 552,327\n베니 8,075\n제니 9,580 \n\n명성\n    5,722 \n\n획득스킬\n    \n\n\n[주소복사](javascript:void\\(0\\);) <https://www.inven.co.kr/board/lineageclassic/6482/13177>\n",
  "images": []
}